pygrype/__init__.py
pygrype/grype.py
pygrype/grype_db.py
pygrype/logging.py
pygrype/core/__init__.py
pygrype/core/grype_version.py
pygrype/core/backends/__init__.py
pygrype/core/backends/base.py
pygrype/core/backends/binary.py
pygrype/core/backends/docker.py
pygrype/core/decorators/to_json.py
pygrype/core/exceptions/GrypeNotAvailableException.py
pygrype/core/exceptions/__init__.py
pygrype/core/list/db_meta_data.py
pygrype/core/scan/artifact.py
pygrype/core/scan/cvss.py
pygrype/core/scan/cvss_metrics.py
pygrype/core/scan/distro.py
pygrype/core/scan/layer.py
pygrype/core/scan/location.py
pygrype/core/scan/match.py
pygrype/core/scan/match_details.py
pygrype/core/scan/match_details_found.py
pygrype/core/scan/match_details_searched_by.py
pygrype/core/scan/package.py
pygrype/core/scan/scan.py
pygrype/core/scan/scan_source.py
pygrype/core/scan/searched_by_distro.py
pygrype/core/scan/target.py
pygrype/core/scan/upstream.py
pygrype/core/scan/vulnerability.py
pygrype/core/scan/vulnerability_fix.py
pygrype-0.4.0.dist-info/LICENSE
pygrype-0.4.0.dist-info/METADATA
pygrype-0.4.0.dist-info/WHEEL
pygrype-0.4.0.dist-info/top_level.txt
pygrype-0.4.0.dist-info/RECORD
